docx2txt/__init__.py
docx2txt/task.py
mm_docx2txt-0.3.0.dist-info/METADATA
mm_docx2txt-0.3.0.dist-info/WHEEL
mm_docx2txt-0.3.0.dist-info/RECORD
