Metadata-Version: 2.1
Name: mm-docx2txt
Version: 0.3.0
Summary: 
Author: hud
Author-email: hudwahab@gmail.com
Requires-Python: >=3.9,<3.12
Classifier: Programming Language :: Python :: 3
Classifier: Programming Language :: Python :: 3.9
Classifier: Programming Language :: Python :: 3.10
Classifier: Programming Language :: Python :: 3.11
Requires-Dist: flytekit (==1.10.0)
Requires-Dist: pytest (>=7.4.2,<8.0.0)
